{
  "sourceEntity": {
    "datasetId": "employeeterritories-d_oe",
    "name": "EmployeeTerritories",
    "projectId": "{{ref(project.current.projectId)}}",
    "taskId": "transform_25-d_oa"
  },
  "targetEntity": {
    "datasetId": "employees-d_oc",
    "name": "Employees",
    "projectId": "{{ref(project.current.projectId)}}",
    "taskId": "transform_25-d_oa"
  },
  "columnRelationships": [
    {
      "sourceColumn": "EmployeeID",
      "targetColumn": "EmployeeID",
      "sourceColumnId": "employeeid",
      "targetColumnId": "employeeid"
    }
  ],
  "name": "EmployeeTerritories_Employees_relation",
  "description": "",
  "id": "employeeterritories_employees_relation-w-td"
}